README.md
setup.py
rna_moccasin/__init__.py
rna_moccasin.egg-info/PKG-INFO
rna_moccasin.egg-info/SOURCES.txt
rna_moccasin.egg-info/dependency_links.txt
rna_moccasin.egg-info/top_level.txt