Metadata-Version: 2.1
Name: rna-moccasin
Version: 0.0.1
Summary: dummy package for rna_moccasin
Home-page: https://majiq.biociphers.org/
Author: BioCiphers
Author-email: admin@biociphers.org
License: MIT License
Platform: UNKNOWN
Classifier: Programming Language :: Python :: 3
Classifier: Operating System :: OS Independent
